motrack/__init__.py
motrack/version.py
motrack/cmc/__init__.py
motrack/cmc/catalog.py
motrack/cmc/factory.py
motrack/cmc/algorithms/__init__.py
motrack/cmc/algorithms/base.py
motrack/cmc/algorithms/gmc_from_file.py
motrack/common/__init__.py
motrack/common/formats.py
motrack/common/project.py
motrack/config_parser/__init__.py
motrack/config_parser/core.py
motrack/datasets/__init__.py
motrack/datasets/base.py
motrack/datasets/catalog.py
motrack/datasets/factory.py
motrack/datasets/mot.py
motrack/evaluation/__init__.py
motrack/evaluation/io.py
motrack/filter/__init__.py
motrack/filter/catalog.py
motrack/filter/factory.py
motrack/filter/algorithms/__init__.py
motrack/filter/algorithms/base.py
motrack/filter/algorithms/end_to_end.py
motrack/filter/algorithms/kalman_filter.py
motrack/filter/algorithms/no_motion.py
motrack/library/__init__.py
motrack/library/cv/__init__.py
motrack/library/cv/bbox.py
motrack/library/cv/color_palette.py
motrack/library/cv/drawing.py
motrack/library/cv/video_reader.py
motrack/library/cv/video_writer.py
motrack/library/kalman_filter/__init__.py
motrack/library/kalman_filter/botsort_kf.py
motrack/library/kalman_filter/conf_kf.py
motrack/library/numpy_utils/__init__.py
motrack/library/numpy_utils/bbox.py
motrack/library/numpy_utils/io.py
motrack/object_detection/__init__.py
motrack/object_detection/catalog.py
motrack/object_detection/factory.py
motrack/object_detection/manager.py
motrack/object_detection/algorithms/__init__.py
motrack/object_detection/algorithms/base.py
motrack/object_detection/algorithms/yolov8.py
motrack/object_detection/algorithms/yolox.py
motrack/object_detection/yolox/__init__.py
motrack/object_detection/yolox/core.py
motrack/object_detection/yolox/yolox_x.py
motrack/reid/__init__.py
motrack/reid/catalog.py
motrack/reid/factory.py
motrack/reid/algorithms/__init__.py
motrack/reid/algorithms/base.py
motrack/reid/algorithms/fastreid_onnx.py
motrack/tools/__init__.py
motrack/tools/inference.py
motrack/tools/mining.py
motrack-0.4.1.dist-info/LICENSE
motrack-0.4.1.dist-info/METADATA
motrack-0.4.1.dist-info/WHEEL
motrack-0.4.1.dist-info/top_level.txt
motrack-0.4.1.dist-info/RECORD
