Metadata-Version: 2.1
Name: motrack
Version: 0.4.1
Summary: Tracking-by-detection (MOT) package
Home-page: https://github.com/Robotmurlock/Motrack
Author: Momir Adzemovic
Author-email: momir.adzemovic@gmail.com
Keywords: tracking-by-detection,multi-object-tracking
Classifier: Development Status :: 3 - Alpha
Classifier: Intended Audience :: Developers
Classifier: Topic :: Software Development :: Build Tools
Classifier: Programming Language :: Python :: 3
Classifier: Programming Language :: Python :: 3.8
Classifier: Programming Language :: Python :: 3.9
Classifier: Programming Language :: Python :: 3.10
Classifier: Programming Language :: Python :: 3 :: Only
Requires-Python: >=3.8, <4
License-File: LICENSE
Requires-Dist: hydra-core
Requires-Dist: matplotlib
Requires-Dist: numpy
Requires-Dist: omegaconf
Requires-Dist: opencv-python
Requires-Dist: pandas
Requires-Dist: PyYAML
Requires-Dist: scipy
Requires-Dist: tqdm
Requires-Dist: torch
Requires-Dist: motrack-motion
Provides-Extra: motion
Requires-Dist: motrack-motion ; extra == 'motion'
Provides-Extra: reid
Requires-Dist: onnxruntime ; extra == 'reid'
Provides-Extra: yolov8
Requires-Dist: ultralytics ; extra == 'yolov8'
